PrithviWxC/__init__.py
PrithviWxC/model.py
PrithviWxC/rollout.py
PrithviWxC/dataloaders/__init__.py
PrithviWxC/dataloaders/merra2.py
PrithviWxC/dataloaders/merra2_rollout.py
prithviwxc-1.0.0.dist-info/WHEEL
prithviwxc-1.0.0.dist-info/METADATA
prithviwxc-1.0.0.dist-info/RECORD
